[[["ابن حبان", "الثقات لابن حبان", "C:\\Program Files\\Jedli-Windows\\exe.win-amd64-3.4\\texts\\5816.txt", 354]], "C:\\Program Files\\Jedli-Windows\\exe.win-amd64-3.4\\search_results", [{"prefix_lila": "affirmative/energetic particle la-; li- + jussive/subjunctive", "simpleSearch": null, "suffix_nisba": null, "prefix_conjunction": "conjunctions wa- and fa-", "perfect_i": "alif before perfect stem", "suffixes": "all possible combinations of suffixes", "alif_option": 0, "prefix_future": null, "searchregex1": "\\b(?:ف|و){0,1}(?:ب|ل|ك|أ|ا|ت|ي|ن)?(?:ال|لل)?(?:ا|إ)?", "alif_maqs_option": "final yā’ = alif maqṣūra", "input": "judges.txt", "suffix_pronom": null, "checklist_name": "C:/Program Files/Jedli-Windows/exe.win-amd64-3.4/checklists/judges.txt", "prefix_interr": null, "suffix_case": null, "prefix_masdar": null, "words_regex": ["\\b(?:ف|و){0,1}(?:ب|ل|ك|أ|ا|ت|ي|ن)?(?:ال|لل)?(?:ا|إ)?قاض(?:و|ن|ه|ى|ا|تما|ها|نا|ت|تم|هم|كم|ة|كما|تمو|كن|هما|ي|وا|ني|ات|هن|تن|ك|تا){0,4}\\b", "\\b(?:ف|و){0,1}(?:ب|ل|ك|أ|ا|ت|ي|ن)?(?:ال|لل)?(?:ا|إ)?ستقض(?:و|ن|ه|ى|ا|تما|ها|نا|ت|تم|هم|كم|ة|كما|تمو|كن|هما|ي|وا|ني|ات|هن|تن|ك|تا){0,4}\\b", "\\b(?:ف|و){0,1}(?:ب|ل|ك|أ|ا|ت|ي|ن)?(?:ال|لل)?(?:ا|إ)?قضا[(?:ة|(?:ت\\B))ء](?:و|ن|ه|ى|ا|تما|ها|نا|ت|تم|هم|كم|ة|كما|تمو|كن|هما|ي|وا|ني|ات|هن|تن|ك|تا){0,4}\\b", "\\b(?:ف|و){0,1}(?:ب|ل|ك|أ|ا|ت|ي|ن)?(?:ال|لل)?(?:ا|إ)?قض(?:ى|ي|(?:ا\\B))(?:و|ن|ه|ى|ا|تما|ها|نا|ت|تم|هم|كم|ة|كما|تمو|كن|هما|ي|وا|ني|ات|هن|تن|ك|تا){0,4}\\b"], "prefix_personal": "personal prefixes (verbs)", "prefixes": "all possible combinations of prefixes", "prefix_preposition": "prepositions ka-, bi- and li-", "suffix_verb_infl": null, "ta_marb_option": 0, "prefix_article": "article al-", "and_or_not": "AND", "searchregex2": "(?:و|ن|ه|ى|ا|تما|ها|نا|ت|تم|هم|كم|ة|كما|تمو|كن|هما|ي|وا|ني|ات|هن|تن|ك|تا){0,4}\\b", "words": ["قاض", "ستقض", "قضا[ةء]", "قضى"]}, {"prefix_lila": null, "simpleSearch": null, "suffix_nisba": null, "prefix_conjunction": "conjunctions wa- and fa-", "perfect_i": null, "suffixes": "no suffixes allowed", "alif_option": "any alif-hamza combination", "prefix_future": null, "searchregex1": "\\b(?:ف|و){0,1}(?:ب|ل|ك)?", "alif_maqs_option": "final yā’ = alif maqṣūra", "input": "ChecklistfarsShort.txt", "suffix_pronom": null, "checklist_name": "C:/Program Files/Jedli-Windows/exe.win-amd64-3.4/checklists/ChecklistfarsShort.txt", "prefix_interr": null, "suffix_case": null, "prefix_masdar": null, "words_regex": ["\\b(?:ف|و){0,1}(?:ب|ل|ك)?سير[اإآأ]ف\\b", "\\b(?:ف|و){0,1}(?:ب|ل|ك)?س[اإآأ]بور\\b", "\\b(?:ف|و){0,1}(?:ب|ل|ك)?ك[اإآأ]زرون\\b", "\\b(?:ف|و){0,1}(?:ب|ل|ك)?جور\\b", "\\b(?:ف|و){0,1}(?:ب|ل|ك)?شير[اإآأ]ز\\b", "\\b(?:ف|و){0,1}(?:ب|ل|ك)?[اإآأ]صطخر\\b", "\\b(?:ف|و){0,1}(?:ب|ل|ك)?در[اإآأ]بجرد\\b", "\\b(?:ف|و){0,1}(?:ب|ل|ك)?[اإآأ]ر[اإآأ]ج[اإآأ]ن\\b", "\\b(?:ف|و){0,1}(?:ب|ل|ك)?[اإآأ]رج[اإآأ]ن\\b", "\\b(?:ف|و){0,1}(?:ب|ل|ك)?ف[اإآأ]رس\\b", "\\b(?:ف|و){0,1}(?:ب|ل|ك)?[اإآأ]ردشير(?:\\W|\\d|الصفح(?:ة|ه|(?:ت\\B)):|الجزء:|الحديث:)+خر(?:ة|ه|(?:ت\\B))\\b", "\\b(?:ف|و){0,1}(?:ب|ل|ك)?د[اإآأ]ر[اإآأ]بجرد\\b", "\\b(?:ف|و){0,1}(?:ب|ل|ك)?نوبنج[اإآأ]ن\\b", "\\b(?:ف|و){0,1}(?:ب|ل|ك)?توج\\b"], "prefix_personal": null, "prefixes": "all possible combinations of prefixes", "prefix_preposition": "prepositions ka-, bi- and li-", "suffix_verb_infl": null, "ta_marb_option": "final hā’ = tā’ marbūṭa", "prefix_article": null, "and_or_not": "AND", "searchregex2": "\\b", "words": ["سيراف", "سابور", "كازرون", "جور", "شيراز", "أصطخر", "درابجرد", "اراجان", "ارجان", "فارس", "أردشير خرة", "دارابجرد", "نوبنجان", "توج"]}, {"prefix_lila": null, "simpleSearch": null, "suffix_nisba": null, "prefix_conjunction": null, "perfect_i": null, "suffixes": "no suffixes allowed", "alif_option": "any alif-hamza combination", "prefix_future": null, "searchregex1": "\\b(?:ا|أ|و|ف|ل|س|ت|ي|ن|إ|م|ك|ب){0,6}", "alif_maqs_option": "final yā’ = alif maqṣūra", "input": "ChecklistfarsRed.txt", "suffix_pronom": null, "checklist_name": "C:/Program Files/Jedli-Windows/exe.win-amd64-3.4/checklists/ChecklistfarsRed.txt", "prefix_interr": null, "suffix_case": null, "prefix_masdar": null, "words_regex": ["\\b(?:ا|أ|و|ف|ل|س|ت|ي|ن|إ|م|ك|ب){0,6}[اإآأ]لف(?:\\W|\\d|الصفح(?:ة|ه|(?:ت\\B)):|الجزء:|الحديث:)+ف[اإآأ]رس\\b", "\\b(?:ا|أ|و|ف|ل|س|ت|ي|ن|إ|م|ك|ب){0,6}[اإآأ]ل[اإآأ]ف(?:\\W|\\d|الصفح(?:ة|ه|(?:ت\\B)):|الجزء:|الحديث:)+ف[اإآأ]رس\\b", "\\b(?:ا|أ|و|ف|ل|س|ت|ي|ن|إ|م|ك|ب){0,6}م[اإآأ]س(?:\\W|\\d|الصفح(?:ة|ه|(?:ت\\B)):|الجزء:|الحديث:)+قومس\\b", "\\b(?:ا|أ|و|ف|ل|س|ت|ي|ن|إ|م|ك|ب){0,6}[اإآأ]لف[اإآأ]رس\\b", "\\b(?:ا|أ|و|ف|ل|س|ت|ي|ن|إ|م|ك|ب){0,6}بهر[اإآأ]م(?:\\W|\\d|الصفح(?:ة|ه|(?:ت\\B)):|الجزء:|الحديث:)+جور\\b", "\\b(?:ا|أ|و|ف|ل|س|ت|ي|ن|إ|م|ك|ب){0,6}بن(?:\\W|\\d|الصفح(?:ة|ه|(?:ت\\B)):|الجزء:|الحديث:)+[اإآأ]ب[اإآأ]ن\\b", "\\b(?:ا|أ|و|ف|ل|س|ت|ي|ن|إ|م|ك|ب){0,6}م[اإآأ]ئ(?:ة|ه|(?:ت\\B))(?:\\W|\\d|الصفح(?:ة|ه|(?:ت\\B)):|الجزء:|الحديث:)+ف[اإآأ]رس\\b", "\\b(?:ا|أ|و|ف|ل|س|ت|ي|ن|إ|م|ك|ب){0,6}س[اإآأ]بور(?:\\W|\\d|الصفح(?:ة|ه|(?:ت\\B)):|الجزء:|الحديث:)+ذ(?:ى|ي|(?:ا\\B))(?:\\W|\\d|الصفح(?:ة|ه|(?:ت\\B)):|الجزء:|الحديث:)+[اإآأ]ل[اإآأ]كت[اإآأ]ف\\b", "\\b(?:ا|أ|و|ف|ل|س|ت|ي|ن|إ|م|ك|ب){0,6}س[اإآأ]بور(?:\\W|\\d|الصفح(?:ة|ه|(?:ت\\B)):|الجزء:|الحديث:)+ذو(?:\\W|\\d|الصفح(?:ة|ه|(?:ت\\B)):|الجزء:|الحديث:)+[اإآأ]ل[اإآأ]كت[اإآأ]ف\\b", "\\b(?:ا|أ|و|ف|ل|س|ت|ي|ن|إ|م|ك|ب){0,6}بن(?:\\W|\\d|الصفح(?:ة|ه|(?:ت\\B)):|الجزء:|الحديث:)+س[اإآأ]بور\\b", "\\b(?:ا|أ|و|ف|ل|س|ت|ي|ن|إ|م|ك|ب){0,6}[اإآأ]ب(?:ى|ي|(?:ا\\B))(?:\\W|\\d|الصفح(?:ة|ه|(?:ت\\B)):|الجزء:|الحديث:)+بكر(?:ة|ه|(?:ت\\B))\\b", "\\b(?:ا|أ|و|ف|ل|س|ت|ي|ن|إ|م|ك|ب){0,6}[اإآأ]بو(?:\\W|\\d|الصفح(?:ة|ه|(?:ت\\B)):|الجزء:|الحديث:)+بكر(?:ة|ه|(?:ت\\B))\\b", "\\b(?:ا|أ|و|ف|ل|س|ت|ي|ن|إ|م|ك|ب){0,6}ل[اإآأ](?:\\W|\\d|الصفح(?:ة|ه|(?:ت\\B)):|الجزء:|الحديث:)+ب[اإآأ]س\\b", "\\b(?:ا|أ|و|ف|ل|س|ت|ي|ن|إ|م|ك|ب){0,6}ملك(?:\\W|\\d|الصفح(?:ة|ه|(?:ت\\B)):|الجزء:|الحديث:)+ف[اإآأ]رس\\b", "\\b(?:ا|أ|و|ف|ل|س|ت|ي|ن|إ|م|ك|ب){0,6}ملوك(?:\\W|\\d|الصفح(?:ة|ه|(?:ت\\B)):|الجزء:|الحديث:)+ف[اإآأ]رس\\b", "\\b(?:ا|أ|و|ف|ل|س|ت|ي|ن|إ|م|ك|ب){0,6}[اإآأ]?بن(?:\\W|\\d|الصفح(?:ة|ه|(?:ت\\B)):|الجزء:|الحديث:)+ف[اإآأ]رس\\b", "\\b(?:ا|أ|و|ف|ل|س|ت|ي|ن|إ|م|ك|ب){0,6}جند(?:ى|ي|(?:ا\\B))(?:\\W|\\d|الصفح(?:ة|ه|(?:ت\\B)):|الجزء:|الحديث:)+س[اإآأ]بور\\b", "\\b(?:ا|أ|و|ف|ل|س|ت|ي|ن|إ|م|ك|ب){0,6}جند(?:ى|ي|(?:ا\\B))(?:\\W|\\d|الصفح(?:ة|ه|(?:ت\\B)):|الجزء:|الحديث:)+س[اإآأ]بور\\b", "\\b(?:ا|أ|و|ف|ل|س|ت|ي|ن|إ|م|ك|ب){0,6}[اإآأ]لجور\\b", "\\b(?:ا|أ|و|ف|ل|س|ت|ي|ن|إ|م|ك|ب){0,6}ل(?:ة|ه|(?:ت\\B))(?:\\W|\\d|الصفح(?:ة|ه|(?:ت\\B)):|الجزء:|الحديث:)+ب[اإآأ]ب[اإآأ]ن\\b", "\\b(?:ا|أ|و|ف|ل|س|ت|ي|ن|إ|م|ك|ب){0,6}ل(?:ة|ه|(?:ت\\B))[اإآأ](?:\\W|\\d|الصفح(?:ة|ه|(?:ت\\B)):|الجزء:|الحديث:)+ب[اإآأ]ب[اإآأ]ن\\b", "\\b(?:ا|أ|و|ف|ل|س|ت|ي|ن|إ|م|ك|ب){0,6}[اإآأ]جور\\b", "\\b(?:ا|أ|و|ف|ل|س|ت|ي|ن|إ|م|ك|ب){0,6}[اإآأ]لفجور\\b"], "prefix_personal": null, "prefixes": "all possible combinations of prefixes", "prefix_preposition": null, "suffix_verb_infl": null, "ta_marb_option": "final hā’ = tā’ marbūṭa", "prefix_article": null, "and_or_not": "NOT", "searchregex2": "\\b", "words": ["ألف فارس", "آلاف فارس", "ماس قومس", "الفارس", "بهرام جور", "بن أبان", "مائة فارس", "سابور ذي الأكتاف", "سابور ذو الأكتاف", "بن سابور", "أبي بكرة", "أبو بكرة", "لا بأس", "ملك فارس", "ملوك فارس", "ا?بن فارس", "جندي سابور", "جندى سابور", "الجور", "له بابان", "لها بابان", "أجور", "الفجور"]}]]